README.txt
setup.cfg
setup.py
adi/__init__.py
adi.fullscreen.egg-info/PKG-INFO
adi.fullscreen.egg-info/SOURCES.txt
adi.fullscreen.egg-info/dependency_links.txt
adi.fullscreen.egg-info/entry_points.txt
adi.fullscreen.egg-info/namespace_packages.txt
adi.fullscreen.egg-info/not-zip-safe
adi.fullscreen.egg-info/paster_plugins.txt
adi.fullscreen.egg-info/requires.txt
adi.fullscreen.egg-info/top_level.txt
adi/fullscreen/__init__.py
adi/fullscreen/configure.zcml
adi/fullscreen/tests.py
adi/fullscreen/browser/__init__.py
adi/fullscreen/browser/configure.zcml
adi/fullscreen/browser/interfaces.py
adi/fullscreen/browser/sitefullscreen.js
adi/fullscreen/browser/toggle_sitefullscreen.pt
adi/fullscreen/browser/viewlets.py
adi/fullscreen/profiles/default/browserlayer.xml
adi/fullscreen/profiles/default/jsregistry.xml
adi/fullscreen/profiles/default/metadata.xml
docs/HISTORY.txt
docs/INSTALL.txt
docs/LICENSE.GPL
docs/LICENSE.txt