Metadata-Version: 1.0
Name: adi.fullscreen
Version: 0.2
Summary: Give the possibilty of fullscreenmode for plonsite by click.
Home-page: http://svn.plone.org/svn/collective/adi.fullscreen
Author: Ida Ebkes
Author-email: contact@ida-ebkes.eu
License: GPL
Platform: UNKNOWN
Classifier: Framework :: Plone
Classifier: Programming Language :: Python
